admin_helpers/__init__.py
admin_helpers/apps.py
admin_helpers/context_processors.py
admin_helpers/settings.py
admin_helpers/utils.py
admin_helpers/actions/__init__.py
admin_helpers/actions/apps.py
admin_helpers/actions/static/object_actions/js/model_actions.js
admin_helpers/global_search/__init__.py
admin_helpers/global_search/apps.py
admin_helpers/global_search/mixin.py
admin_helpers/global_search/search_helper.py
admin_helpers/global_search/urls.py
admin_helpers/global_search/views.py
admin_helpers/global_search/backends/__init__.py
admin_helpers/global_search/backends/base.py
admin_helpers/global_search/backends/model.py
admin_helpers/global_search/static/global_search/js/global_search.js
admin_helpers/static/admin_helpers/css/helpers.css
admin_helpers/static/admin_helpers/fontawesome/css/all.css
admin_helpers/static/admin_helpers/fontawesome/css/all.min.css
admin_helpers/static/admin_helpers/fontawesome/css/brands.css
admin_helpers/static/admin_helpers/fontawesome/css/brands.min.css
admin_helpers/static/admin_helpers/fontawesome/css/fontawesome.css
admin_helpers/static/admin_helpers/fontawesome/css/fontawesome.min.css
admin_helpers/static/admin_helpers/fontawesome/css/regular.css
admin_helpers/static/admin_helpers/fontawesome/css/regular.min.css
admin_helpers/static/admin_helpers/fontawesome/css/solid.css
admin_helpers/static/admin_helpers/fontawesome/css/solid.min.css
admin_helpers/static/admin_helpers/fontawesome/css/svg-with-js.css
admin_helpers/static/admin_helpers/fontawesome/css/svg-with-js.min.css
admin_helpers/static/admin_helpers/fontawesome/css/v4-font-face.css
admin_helpers/static/admin_helpers/fontawesome/css/v4-font-face.min.css
admin_helpers/static/admin_helpers/fontawesome/css/v4-shims.css
admin_helpers/static/admin_helpers/fontawesome/css/v4-shims.min.css
admin_helpers/static/admin_helpers/fontawesome/css/v5-font-face.css
admin_helpers/static/admin_helpers/fontawesome/css/v5-font-face.min.css
admin_dj_helpers-0.1.0.dist-info/METADATA
admin_dj_helpers-0.1.0.dist-info/WHEEL
admin_dj_helpers-0.1.0.dist-info/licenses/LICENSE
admin_dj_helpers-0.1.0.dist-info/RECORD
